{
  "bootstrap-sha": "5e4083e29153fe65960535a6cfd3cc926ba48346",
  "packages": {
    ".": {
      "release-type": "simple",
      "package-name": "valhalla-user",
      "changelog-path": "CHANGELOG.md",
      "include-v-in-tag": true,
      "extra-files": [
        {
          "type": "xml",
          "path": "pom.xml",
          "xpath": "/project/properties/revision"
        }
      ],
      "changelog-sections": [
        {
          "type": "feat",
          "section": "Features"
        },
        {
          "type": "fix",
          "section": "Bug Fixes"
        },
        {
          "type": "docs",
          "section": "Documentation"
        },
        {
          "type": "refactor",
          "section": "Code Refactoring"
        },
        {
          "type": "perf",
          "section": "Performance Improvements"
        },
        {
          "type": "test",
          "section": "Tests"
        },
        {
          "type": "build",
          "section": "Build System"
        },
        {
          "type": "ci",
          "section": "Continuous Integration"
        },
        {
          "type": "chore",
          "section": "Miscellaneous Chores"
        }
      ]
    }
  },
  "$schema": "https://raw.githubusercontent.com/googleapis/release-please/main/schemas/config.json"
}
